mattress_mcp/__init__.py
mattress_mcp/__main__.py
mattress_mcp/server.py
mattress_mcp_xyt-0.0.1.dist-info/licenses/LICENSE
mattress_mcp_xyt-0.0.1.dist-info/METADATA
mattress_mcp_xyt-0.0.1.dist-info/WHEEL
mattress_mcp_xyt-0.0.1.dist-info/entry_points.txt
mattress_mcp_xyt-0.0.1.dist-info/top_level.txt
mattress_mcp_xyt-0.0.1.dist-info/RECORD
